qat/comm/__init__.so
qat/comm/cast_result.so
qat/comm/logs.so
qat/comm/map_converter.so
qat/comm/thrift_utils.so
qat/comm/utils.so
qat/comm/version.so
qat/comm/application/Application.so
qat/comm/application/BatchGenerator.so
qat/comm/application/__init__.so
qat/comm/application/constants.so
qat/comm/application/ttypes.so
qat/comm/datamodel/__init__.so
qat/comm/datamodel/constants.so
qat/comm/datamodel/ttypes.so
qat/comm/exceptions/__init__.so
qat/comm/exceptions/_ttypes.so
qat/comm/exceptions/constants.so
qat/comm/exceptions/ttypes.so
qat/comm/gate_set/__init__.so
qat/comm/gate_set/constants.so
qat/comm/gate_set/ttypes.so
qat/comm/hardware/__init__.so
qat/comm/hardware/constants.so
qat/comm/hardware/ttypes.so
qat/comm/noisy/__init__.so
qat/comm/noisy/constants.so
qat/comm/noisy/ttypes.so
qat/comm/observable/__init__.so
qat/comm/observable/constants.so
qat/comm/observable/ttypes.so
qat/comm/parameter/__init__.so
qat/comm/parameter/constants.so
qat/comm/parameter/ttypes.so
qat/comm/qpu/Plugin.so
qat/comm/qpu/QPU.so
qat/comm/qpu/__init__.so
qat/comm/qpu/constants.so
qat/comm/qpu/ttypes.so
qat/comm/quops/__init__.so
qat/comm/quops/constants.so
qat/comm/quops/ttypes.so
qat/comm/resource/ResourceManager.so
qat/comm/resource/__init__.so
qat/comm/resource/constants.so
qat/comm/resource/ttypes.so
qat/comm/shared/__init__.so
qat/comm/shared/constants.so
qat/comm/shared/ttypes.so
qat_comm-1.8.0.dist-info/licenses/LICENSE.txt
qat_comm-1.8.0.dist-info/METADATA
qat_comm-1.8.0.dist-info/WHEEL
qat_comm-1.8.0.dist-info/top_level.txt
qat_comm-1.8.0.dist-info/RECORD
